kms_encryption_key/__init__.py
kms_encryption_key/py.typed
kms_encryption_key/_jsii/__init__.py
kms_encryption_key/_jsii/kms-encryption-key@0.0.5.jsii.tgz
kms_encryption_key-0.0.5.dist-info/LICENSE
kms_encryption_key-0.0.5.dist-info/METADATA
kms_encryption_key-0.0.5.dist-info/WHEEL
kms_encryption_key-0.0.5.dist-info/top_level.txt
kms_encryption_key-0.0.5.dist-info/RECORD
